{
  "title": "A Spectrum of Nova Delphini",
  "explanation": "<b>  </b>\n\n<a href=\"ap130816.html\">When a new star</a>\nappeared in the constellation Delphinus late last week,\n<a href=\"http://www.aavso.org/aavso-alert-notice-489\">astronomers\nfound</a> its spectrum hinted at the apparition's true nature.\n\nNow known as Nova Delphini 2013, its\n<a href=\"ap100627.html\">visible light spectrum</a> near \n<a href=\"http://www.aavso.org/whats-store-nova-del-2013\">maximum\nbrightness</a>\nis centered in this image of the nearby\n<a href=\"http://stargazerslounge.com/topic/\n192824-nova-del-2013-picspectrum/\">star field</a> captured with\n<a href=\"http://www.youtube.com/watch?v=uucYGK_Ymp0\">prism</a> and\ntelescope on the night of August 16/17 at the\n<a href=\"http://sternwartebuelach.ch/\">Sternwarte Bülach</a>,\nSwitzerland.\n\nStrong <a href=\"http://csep10.phys.utk.edu/astr162/lect/light/\nabsorption.html\">absorption lines</a> due to hydrogen atoms\nare seen as the darkest bands in the nova's spectrum, but\nthe strong absorption lines are bordered along their redward edge by bright\nbands of emission.\n\nThat pattern is the\n<a href=\"http://en.wikipedia.org/wiki/P_Cygni\">spectral signature</a>\nof material blasted from\na type of catalysmic binary system known as\n<a href=\"ap091117.html\">a classical nova</a>.\n\nOther stars in field are fainter, identified by their\n<a href=\"http://en.wikipedia.org/wiki/Hipparcos_catalog\">Hip</a>parcus\ncatalog numbers, brightness in\n<a href=\"http://en.wikipedia.org/wiki/\nMagnitude_%28astronomy%29\">magnitudes</a>, and\n<a href=\"ap040418.html\">spectral types</a>.\n\nBy chance, the faint emission line from\n<a href=\"ap121004.html\">planetary nebula</a> NGC 6905\nwas also included, indicated at the lower right.",
  "date": "2013-08-23",
  "hdurl": "https://apod.nasa.gov/apod/image/1308/nova_del_labels_Alean.jpg",
  "service_version": "v1",
  "copyright": "Jürg Alean",
  "media_type": "image",
  "url": "https://apod.nasa.gov/apod/image/1308/nova_del_labels_Alean.jpg"
}