{
  "title": "Rays from an Unexpected Aurora",
  "explanation": "<b>  </b>\n\nThis aurora was a bit of a surprise.  \n\nFor starters, on this day in 2002, no intense \n<a href=\"http://www.sec.noaa.gov/pmap/\">auroral activity</a> was\nexpected at all.  \n\nPossibly more surprising, however, the \n<a href=\"http://science.nasa.gov/spaceweather/aurora/gallery_01aug02.html\">aurora</a> appeared to show an usual structure of green \n<a href=\"http://www.youtube.com/watch?v=icugqEEOgkg\">rays</a> \nfrom some locations. \n\nIn\n<a href=\"http://science.nasa.gov/spaceweather/aurora/images/01aug02/\nAnderson1.jpg\">this view</a>, captured from \n<a href=\"http://en.wikipedia.org/wiki/North_Dakota\">North Dakota</a>, \n<a href=\"https://www.cia.gov/library/publications/the-world-factbook/\ngeos/us.html\">USA</a>, a picket fence of green rays stretches toward\nthe horizon.  \n\nMirroring the <a href=\"ap000519.html\">green</a> rays is a \n<a href=\"ap020115.html\">red</a> band, somewhat rare in its own right. \n\nLights from the cities of <a href=\"http://www.bismarck.org/\">Bismarck</a> and \n<a href=\"http://en.wikipedia.org/wiki/Mandan%2C_North_Dakota\">Mandan</a> are visible near the horizon.",
  "date": "2008-01-01",
  "hdurl": "https://apod.nasa.gov/apod/image/0801/aurorarays_anderson_big.jpg",
  "service_version": "v1",
  "copyright": "Lyndon Anderson (Prairie Journal)",
  "media_type": "image",
  "url": "https://apod.nasa.gov/apod/image/0801/aurorarays_anderson_big.jpg"
}