{
  "title": "Looking Back at an Eclipsed Earth",
  "credit": "Mir 27 Crew; Copyright: CNES",
  "explanation": "<b>  </b> \nHere is what the Earth looks like during a\n<a href=\"http://www.mreclipse.com/Special/SEprimer.html\">solar eclipse</a>.\n\nThe\n<a href=\"http://www.youtube.com/watch?v=UtgXus3eiII\">shadow</a>\nof the\n<a href=\"ap040829.html\">Moon</a> can be seen darkening part of\n<a href=\"http://antwrp.gsfc.nasa.gov/apod/image/0208/earthlights02_dmsp_big.jpg\">Earth</a>.\n\nThis <a href=\"ap031127.html\">shadow</a> moved\n<a href=\"http://www.youtube.com/watch?v=-EYk_iSpBaE\">across</a> the\n<a href=\"earth.html\">Earth</a> at nearly 2000 kilometers per hour.\n\nOnly observers near the center of the\n<a href=\"ap031208.html\">dark circle</a> see a total solar eclipse -\nothers see a partial eclipse where only part of the\n<a href=\"ap010408.html\">Sun appears blocked by the Moon</a>.\n\nThis <a href=\"http://theastropages.com/articles/articles011.htm\">spectacular picture</a> of the 1999 August 11\n<a href=\"http://eclipse.gsfc.nasa.gov/eclipse.html\">solar eclipse</a>\nwas one of the last ever\ntaken from the <a href=\"ap040327.html\">Mir</a> space\n<a href=\"http://en.wikipedia.org/wiki/Mir\">station</a>.\n\nThe two bright spots that \nappear on the upper left are thought to be\n<a href=\"http://theastropages.com/articles/articles011.htm\">Jupiter and Saturn</a>.\n\nMir was <a href=\"ap010323.html\">deorbited</a> in a\n<a href=\"http://www.youtube.com/watch?v=fVQd9Ejkbiw\">controlled re-entry</a> in 2001.",
  "date": "2011-01-02",
  "hdurl": "https://apod.nasa.gov/apod/image/1101/eclipse99_mir_big.jpg",
  "service_version": "v1",
  "copyright": "CNES",
  "media_type": "image",
  "url": "https://apod.nasa.gov/apod/image/1101/eclipse99_mir.jpg"
}