{
  "title": "HDR: Earth's Circular Shadow on the Moon",
  "explanation": "<b>  </b> \nWhat could create such a large circular shadow on the Moon?\n\nThe Earth.\n\nLast week's full Moon -- the \n<a href=\"https://www.timeanddate.com/astronomy/moon/buck.html\">Buck Moon</a> -- was so full that it fell almost exactly \n<a href=\"https://sservi.nasa.gov/articles/eclipse-perspective-what-would-an-astronaut-see-from-the-moon/\">in a line</a> with the \n<a href=\"https://solarsystem.nasa.gov/solar-system/sun/overview/\">Sun</a> and the \n<a href=\"https://solarsystem.nasa.gov/planets/earth/overview/\">Earth</a>. \n\nWhen that happens the Earth casts its \n<a href=\"ap130524.html\">shadow onto the Moon</a>.\n\nThe circularity of the Earth's shadow on the Moon was commented on by \n<a href=\"https://en.wikipedia.org/wiki/Aristotle\">Aristotle</a> and so has \n<a href=\"https://www.aps.org/publications/apsnews/200606/history.cfm\">been noticed since</a> at least the \n<a href=\"https://en.wikipedia.org/wiki/4th_century_BC\">4th century BC</a>.  \n\nWhat's new is humanity's ability to record \n<a href=\"ap190718.html\">this shadow</a> with such \n<a href=\"https://en.wikipedia.org/wiki/High-dynamic-range_imaging\">high dynamic range</a> (HDR). \n\nThe featured HDR composite of last week's partial \n<a href=\"https://eclipse.gsfc.nasa.gov/lunar.html\">lunar eclipse</a> \ncombines 15 images and include an exposure as short as 1/400th of a second -- \nso as not to overexpose the brightest part -- \nand an exposure that lasted five seconds -- \nto bring up the dimmest part.\n\nThis dimmest part -- inside \n<a href=\"ap190126.html\">Earth's umbra</a> -- is \n<a href=\"https://ameliacarruthers.files.wordpress.com/2015/01/black-cat-in-a-dark-room-there-is-nothing-harder.png\">not completely dark</a> \nbecause some \n<a href=\"https://earthsky.org/space/why-does-the-moon-look-red-during-a-total-lunar-eclipse\">light is refracted</a> through the \n<a href=\"ap140803.html\">Earth's atmosphere</a> \n<a href=\"ap190717.html\">onto the Moon</a>. \n\nA <a href=\"ap190120.html\">total lunar eclipse</a> will \n<a href=\"https://eclipse.gsfc.nasa.gov/LEdecade/LEdecade2021.html\">occur next</a> in 2021 May.",
  "date": "2019-07-22",
  "hdurl": "https://apod.nasa.gov/apod/image/1907/PartialLunarEclipse_Fattinnanzi_3345.jpg",
  "service_version": "v1",
  "copyright": "Cristian Fattinnanzi",
  "media_type": "image",
  "url": "https://apod.nasa.gov/apod/image/1907/PartialLunarEclipse_Fattinnanzi_1080.jpg"
}