{
  "title": "Leonid Watching",
  "credit": "APOD Montage",
  "explanation": "<b>  </b>\n\n<a href=\"http://science.msfc.nasa.gov/headlines/y2001/\nast08nov_1.htm\">Will the Leonids storm</a> this year?\n\nThe <a href=\"http://comets.amsmeteors.org/meteors/showers/\nleonidhis.html\">annual Leonid</a> meteor shower should peak\n<a href=\"http://www.spaceweather.com/meteors/leonids/\nobservingtips.html\">this weekend</a> and some\npredictions suggest that \"storm\" rates of a thousand or more meteors\nper hour are possible for observers located in eastern North\nand Central America\nduring the early morning hours of Sunday, November 18.\n\nSimilar high rates are also anticipated for the western Pacific region\non the morning of November 19th.\n\nIn any event, the\n<a href=\"http://leonid.arc.nasa.gov/\">2001 Leonid</a>\nshower should be dramatic and\n<a href=\"http://www.astrosociety.org/pubs/mercury/1101pr/\nleonidsidebar.html\">easy to watch</a>, as were the\n<a href=\"http://science.nasa.gov/newhome/headlines/\nast27nov98%5F1.htm\">Leonids of</a> recent years.\n\nFrom top left to bottom right above are spectacular\n<a href=\"http://leonids.hq.nasa.gov/leonids/photo.html\">examples</a> of\nbright fireball meteors from the 1998 Leonid shower as recorded by\n<a href=\"ap981125.html\">V. Winter and J. Dudley</a>,\n<a href=\"ap991112.html\">Lorenzo Lovato</a>, and\n<a href=\"ap991118.html\">Wally Pacholka</a>.\n\nA 1998 image from the Puckett Observatory at lower left\nfeatures the source of the\n<a href=\"ap001117.html\">debris</a> stream which supplies\nthe Leonid meteors,\n<a href=\"ap991113.html\">comet Tempel-Tuttle</a>.",
  "date": "2001-11-16",
  "hdurl": "https://apod.nasa.gov/apod/image/0111/leo98_apodmontage_big.jpg",
  "service_version": "v1",
  "media_type": "image",
  "url": "https://apod.nasa.gov/apod/image/0111/leo98_apodc2.jpg"
}