{
  "title": "Red Aurora over Poland",
  "explanation": "<b>  </b> \nNorthern lights don't usually reach this far south. \n\nMagnetic chaos in the Sun's \n<a href=\"ap240511.html\">huge Active Region 3664</a>, however, produced a surface explosion that sent a \n<a href=\"ap031029.html\">burst</a> of \nelectrons, protons, and more massive, charged nuclei into the \n<a href=\"https://science.nasa.gov/solar-system/facts/\">Solar System</a>.\n\nA few days later, that \n<a href=\"https://en.wikipedia.org/wiki/Coronal_mass_ejection\">coronal mass ejection</a> (CME) impacted the Earth and \n<a href=\"https://www.facebook.com/media/set?set=a.431368006258449&amp;type=3\">triggered auroras</a> that are being reported \nunusually far from our planet's \n<a href=\"https://climatekids.nasa.gov/polar-temperatures/\">north and south poles</a>. \n\nThe free sky show \n<a href=\"https://www.universetoday.com/166942/if-youve-never-seen-an-aurora-before-this-might-be-your-chance/\">might not be over</a> -- \nthe sunspot rich <a href=\"https://skyandtelescope.org/online-gallery/ar3664-ginormous-active-sunspot-area/\">AR3664</a> has ejected even more \n<a href=\"https://www.nasa.gov/image-article/what-coronal-mass-ejection-or-cme/\">CME</a>s that might also impact the \n<a href=\"https://www.swpc.noaa.gov/news/geomagnetic-storming-likely-persist-weekend\">Earth tonight or tomorrow</a>.\n\nThat active region is now \n<a href=\"https://www.spaceweather.com/images2024/11may24/hmi1898.gif\">near the Sun's edge</a>, though, \nand will soon be rotating away from the \n<a href=\"ap161010.html\">Earth</a>. \n\nPictured, a \n<a href=\"ap220220.html\">red</a> and \n<a href=\"ap080101.html\">rayed aurora</a> \nwas captured in a single 6-second exposure from \n<a href=\"https://youtu.be/bMf--MCsLLY\">Racibórz</a>, \n<a href=\"https://en.wikipedia.org/wiki/Poland\">Poland</a> \nearly last night. \n\nThe photographer's friend, seeing an aurora <a href=\"https://as2.ftcdn.net/v2/jpg/01/89/49/89/1000_F_189498933_OeutsN0mMlzJGaJZJvkXIsoSCUCFIO7W.jpg\">for the first time</a>, is visible in the \ndistance also taking images of the \n<a href=\"ap231227.html\">beautifully colorful</a> \nnighttime sky.",
  "date": "2024-05-12",
  "hdurl": "https://apod.nasa.gov/apod/image/2405/AuroraPoland_Durlej_1940.jpg",
  "service_version": "v1",
  "copyright": "Mariusz Durlej",
  "media_type": "image",
  "url": "https://apod.nasa.gov/apod/image/2405/AuroraPoland_Durlej_960.jpg"
}