{
  "title": "Eiffel Tower Prominence on the Sun",
  "explanation": "<b>  </b> \nWhat's that on the Sun?\n\nAlthough it may look like a flowing version of the \n<a href=\"https://en.wikipedia.org/wiki/Eiffel_Tower\">Eiffel Tower</a>, \nit is a \n<a href=\"https://en.wikipedia.org/wiki/Solar_prominence\">solar prominence</a> that is actually much bigger -- about the \n<a href=\"https://spaceweathergallery.com/indiv_upload.php?upload_id=182268\">height of Jupiter</a>.\n\nThe <a href=\"ap220130.html\">huge prominence</a> \nemerged about ten days ago, hovered over the \n<a href=\"ap111106.html\">Sun's surface</a> for about two days, \nand then erupted -- throwing a \n<a href=\"https://www.nasa.gov/content/goddard/what-is-a-coronal-mass-ejection\">coronal mass ejection</a> (CME) into the Solar System.\n\nThe <a href=\"https://www.astrobin.com/andagl/\">featured video</a>, \ncaptured from the astrophotographer's backyard in \n<a href=\"https://en.wikipedia.org/wiki/Hendersonville,_Tennessee\">Hendersonville</a>, \n<a href=\"https://en.wikipedia.org/wiki/Tennessee\">Tennessee</a>, \nUSA, shows an hour time-lapse played both forwards and backwards.\n\nThat CME did not impact the Earth, but our Sun had \n<a href=\"http://1.bp.blogspot.com/-na-Ja9leWR0/TbbqCqVICcI/AAAAAAAAAHs/q6gQNaSY9Ts/s1600/IMG_1606.JPG\">unleashed</a>  \nother recent CMEs that not only triggered \n<a href=\"ap201109.html\">Earthly auroras</a>, but puffed out the \n<a href=\"https://www.nasa.gov/mission_pages/sunearth/science/atmosphere-layers2.html\">Earth's atmosphere</a> enough to \n<a href=\"https://earthsky.org/space/40-starlink-satellites-doomed-by-geomagnetic-storm/\">cause</a> just-launched \n<a href=\"https://en.wikipedia.org/wiki/Starlink\">Starlink</a> satellites to \n<a href=\"https://youtu.be/a7KUSN89-A0?t=68\">fall back</a>.\n\nActivity on the Sun, including \n<a href=\"ap150629.html\">sunspots</a>, \n<a href=\"ap150125.html\">prominences</a>, CMEs and \n<a href=\"ap180902.html\">flare</a>s, continues to increase as the \n<a href=\"https://spaceplace.nasa.gov/all-about-the-sun/en/\">Sun</a> evolves away from a deep \n<a href=\"https://www.nasa.gov/mission_pages/sunearth/news/solarmin-max.html\">minimum</a> in its 11-year \n<a href=\"https://en.wikipedia.org/wiki/Solar_cycle\">magnetic cycle</a>.",
  "date": "2022-02-16",
  "service_version": "v1",
  "copyright": "Hawk Wolinski",
  "media_type": "video",
  "url": "https://www.youtube.com/embed/liapnqj9GDc?rel=0"
}