{
  "title": "Wolf's Cave Nebula",
  "explanation": "<b>  </b> \n<a href=\"https://ui.adsabs.harvard.edu/abs/1908MNRAS..69..117W/abstract\">The mysterious</a> blue reflection nebula found in catalogs as \n<a href=\"https://noirlab.edu/public/images/noao-vdb152/\">VdB 152</a> or Ced 201 really is very faint.\n\nIt lies at the tip of the long\n<a href=\"ap090425.html\">dark nebula</a> Barnard 175 in a\ndusty complex that has also been called\n<a href=\"http://bf-astro.com/vdB152/vdB152.htm\">Wolf's Cave</a>.\n\nAt the center of \n<a href=\"https://www.flickr.com/photos/194921065@N03/52425057847/in/pool-apods/\">this deep telescopic view</a>, the \n<a href=\"/ap201026.html\">cosmic apparitions</a> are nearly 1,400 \n<a href=\"https://exoplanets.nasa.gov/faq/26/what-is-a-light-year/\">light-years</a> away along the northern Milky Way\nin the <a href=\"https://earthsky.org/sky-archive/\nconstellation-cepheus-looks-like-a-house\">royal constellation</a> Cepheus.\n\n<a href=\"https://curator.jsc.nasa.gov/stardust/interstellardust.cfm\">Interstellar dust</a> in the region \n<a href=\"ap201122.html\">blocks light</a> from\nbackground stars and \n<a href=\"https://en.wikipedia.org/wiki/Reflection_nebula\">scatters light</a> from the embedded bright star,\ngiving the end nebula its characteristic blue color.\n\nThough <a href=\"https://coolcosmos.ipac.caltech.edu/infrared_gallery/4\">stars do form</a> in\n<a href=\"https://en.wikipedia.org/wiki/Molecular_cloud\">molecular cloud</a>s, this star\nseems to have only accidentally wandered\ninto the area, as its measured velocity through\nspace is very different from the cloud's velocity.\n\nAt <a href=\"https://www.astrobin.com/bxbmqc/\">the image</a> bottom is the planetary nebula \n<a href=\"https://astrodonimaging.com/gallery/dengel-hartl-5-in-cepheus/\">Dengel-Hartl 5</a>, while\nred glowing gas from an ancient supernova remnant is \n<a href=\"http://bf-astro.com/vdB152/vdB152.htm\">also visible</a> along the image's right side.",
  "date": "2022-11-15",
  "hdurl": "https://apod.nasa.gov/apod/image/2211/WolfsCave_Lacroce_3053.jpg",
  "service_version": "v1",
  "copyright": "Gianni Lacroce",
  "media_type": "image",
  "url": "https://apod.nasa.gov/apod/image/2211/WolfsCave_Lacroce_960.jpg"
}