{
  "title": "Asteroid Gaspra's Best Face",
  "credit": "The Galileo Project, NASA",
  "explanation": "<b>  </b> \n\nAsteroid \n<a href=\"http://www.jpl.nasa.gov/galileo/bestgaspra.html\">951 Gaspra</a> is a huge rock tumbling in space.  \n<a href=\"http://www.nineplanets.org/gaspra.html\">Gaspra</a> became one of the best-studied \n<a href=\"http://www.solarviews.com/eng/gaspra.htm\">asteroids</a> in 1991 when the \n<a href=\"http://www.jpl.nasa.gov/galileo/spacecraft.html\">spacecraft Galileo</a> flew by.\n\nIn the \n<a href=\"http://photojournal.jpl.nasa.gov/catalog/PIA00119\">above photograph</a>, subtle color variations have been \nexaggerated to highlight changes in reflectivity, \nsurface structure and composition. \n\n<a href=\"http://nssdc.gsfc.nasa.gov/photo_gallery/photogallery-asteroids.html\">Gaspra</a> is about 20 kilometers long and orbits the \n<a href=\"ap980830.html\">Sun</a> in the \n<a href=\"ap020724.html\">main asteroid belt</a> between \n<a href=\"http://mars.jpl.nasa.gov/\">Mars</a> and \n<a href=\"http://www.nineplanets.org/jupiter.html\">Jupiter</a>.",
  "date": "2002-10-27",
  "hdurl": "https://apod.nasa.gov/apod/image/0210/gaspra_galileo_big.gif",
  "service_version": "v1",
  "media_type": "image",
  "url": "https://apod.nasa.gov/apod/image/0210/gaspra_galileo.jpg"
}