{
  "title": "Beagle Crater on Mars",
  "credit": "Mars Exploration Rover Mission, Cornell, JPL, NASA",
  "explanation": "<b>  </b>\nWhat have we found on the way to large Victoria Crater?  \n\nSmaller <a href=\"http://en.wikipedia.org/wiki/Beagle_(crater)\">Beagle Crater</a>.  \n\nThe robotic \n<a href=\"ap051214.html\">Opportunity rover</a> rolling across \n<a href=\"http://www.nineplanets.org/mars.html\">Mars</a> stopped at <a href=\"http://www.marsdaily.com/reports/Beagle_Crater_Is_Next_Stop_For_Opportunity_999.html\">Beagle Crater</a> early last month and took an \n<a href=\"image/0609/beaglecrater_opportunity_big.jpg\">impressively detailed</a> 360-degree \n<a href=\"ap010918.html\">panorama</a> of the alien Martian landscape.  \n\nBeagle crater appears in the center as a dip exposing relatively \n<a href=\"ap051108.html\">dark sand</a>.\n\nSurrounding 35-meter Beagle Crater are many of the rocks ejected during its creation impact.  \n\nOpportunity's \n<a href=\"http://photojournal.jpl.nasa.gov/catalog/PIA08753\">detailed image</a>s \nshow significant \n<a href=\"http://en.wikipedia.org/wiki/Erosion\">erosion</a> on the rocks and walls of \nBeagle Crater, indicating that the crater is not fresh.\n\n<a href=\"http://photojournal.jpl.nasa.gov/catalog/PIA08754\">Beagle Crater</a>'s \nunofficial name derives from the ship \n<a href=\"http://en.wikipedia.org/wiki/HMS_Beagle\">HMS Beagle</a> where \n<a href=\" http://www.aboutdarwin.com/\">Charles Darwin</a> \nobservations led him to postulate his theory of \n<a href=\"http://anthro.palomar.edu/evolve/evolve_2.htm\">natural selection</a>.  \n\nThat ship was named after the dog breed of \n<a href=\"http://upload.wikimedia.org/wikipedia/en/7/75/Cadet2.jpg\">beagle</a>.  \n\nOpportunity is scheduled to roll up to expansive \n<a href=\"http://marsrovers.jpl.nasa.gov/mission/tm-opportunity/images/MERB_819_br2.jpg\">Victoria Crater</a> this week.",
  "date": "2006-09-19",
  "hdurl": "https://apod.nasa.gov/apod/image/0609/beaglecrater_opportunity_big.jpg",
  "service_version": "v1",
  "media_type": "image",
  "url": "https://apod.nasa.gov/apod/image/0609/beaglecrater_opportunity.jpg"
}