{
  "title": "The Known Universe",
  "explanation": "<b>  </b>\nWhat would it look like to travel across the known universe?\n\nTo help humanity visualize this, the \n<a href=\"http://www.amnh.org/\">American Museum of Natural History</a> has produced a modern \n<a href=\"http://research.amnh.org/~bro/\">movie featuring</a> many visual highlights of such a trip.\n\n<a href=\"http://www.youtube.com/watch?v=17jymDn0W6U\">The video</a> \nstarts in Earth's \n<a href=\"http://en.wikipedia.org/wiki/Himalayas\">Himalayan Mountains</a> \nand then dramatically zooms out, showing the \n<a href=\"http://earthobservatory.nasa.gov/Features/OrbitsCatalog/\">orbits</a> of \n<a href=\"http://www.nasa.gov/multimedia/imagegallery/image_feature_1283.html\">Earth's satellites</a>, the \n<a href=\"ap090315.html\">Sun</a>, the \n<a href=\"http://space.jpl.nasa.gov/\">Solar System</a>, \nthe extent of humanities \n<a href=\"http://en.wikipedia.org/wiki/Invention_of_radio\">first radio signals</a>, the \n<a href=\"ap080606.html\">Milky Way Galaxy</a>, \n<a href=\"ap071211.html\">galaxies nearby</a>, \n<a href=\"ap091209.html\">distant galaxies</a>, and \n<a href=\"http://en.wikipedia.org/wiki/Quasar\">quasars</a>.  \n\nAs the distant surface of the \n<a href=\" http://en.wikipedia.org/wiki/Microwave_background\">microwave background</a> is finally reached, \n<a href=\"ap031231.html\">radiation</a> is depicted that was emitted billions of light years away and less than one million years after the Big Bang. \n\nFrequently using the \n<a href=\"http://www.haydenplanetarium.org/universe/download\">Digital Universe Atlas</a>, every object in the video \nhas been rendered to scale given the best \n<a href=\"http://www.sciencenews.org/2009/\">scientific research in 2009</a>, \nwhen the video was produced.\n\nThe film has similarities to the famous \n<a href=\"http://www.powersof10.com/\">Powers of Ten</a> \n<a href=\" http://www.youtube.com/watch?v=A2cmlhfdxuY\">video</a> that has been \n<a href=\"http://micro.magnet.fsu.edu/primer/java/scienceopticsu/powersof10/\">a favorite</a> of many space enthusiasts for a generation.",
  "date": "2010-01-20",
  "service_version": "v1",
  "copyright": "American Museum of Natural History",
  "media_type": "other"
}