{
  "title": "The Coma Cluster of Galaxies",
  "explanation": "<b>  </b>\n\nAlmost every object in the above photograph is a galaxy. \n\nThe <a href=\"http://en.wikipedia.org/wiki/Coma_Cluster\">Coma Cluster of Galaxies</a>\n<a href=\"http://deanrowe.net/astro/?image=images/Abell_1656_BRC\">pictured above</a> is one of the densest \n<a href=\"http://www.astr.ua.edu/white/mug/cluster/clusters.html\">clusters</a> known - it contains thousands of \n<a href=\"http://www.seds.org/messier/galaxy.html\">galaxies</a>. \n\nEach of <a href=\"http://www.youtube.com/watch?v=nh7aS5__b4k\">these galaxies</a> houses billions of stars - \njust as our own\n<a href=\"http://www.damtp.cam.ac.uk/research/gr/public/\ngal_milky.html\">Milky Way Galaxy</a> does. \n\nAlthough nearby when compared to most other \n<a href=\"clusters_of_galaxies.html\">clusters</a>, \nlight from the <a href=\"ap080616.html\">Coma Cluster</a> \nstill takes hundreds of millions of years to reach us. \n\nIn fact, the \n<a href=\"http://www.wikisky.org/?object=Coma+Cluster&amp;zoom=9&amp;img_source=DSS2\">Coma Cluster</a> is so big it takes light \nmillions of years just to go from one side to the other! \n\nMost galaxies in <a href=\"\nhttp://imagine.gsfc.nasa.gov/docs/features/objects/coma.html\">Coma</a> and other clusters are \n\n<a href=\"elliptical_galaxies.html\">ellipticals</a>, \nwhile most \n<a href=\"http://www.galaxyzoo.org/\">galaxies</a> outside of clusters are \n<a href=\"spiral_galaxies.html\">spirals</a>. \n\nThe nature of \n<a href=\"http://www.lsw.uni-heidelberg.de/users/mcamenzi/Coma_X.html\">Coma's X-ray emission</a> is \n<a href=\"http://adsabs.harvard.edu/abs/2000A%26A...357...66D\">still being investigated</a>.",
  "date": "2010-05-02",
  "hdurl": "https://apod.nasa.gov/apod/image/1005/comacluster_rowe_big.jpg",
  "service_version": "v1",
  "copyright": "Dean Rowe",
  "media_type": "image",
  "url": "https://apod.nasa.gov/apod/image/1005/comacluster_rowe.jpg"
}