{
  "title": "A Powerful Solar Flare",
  "credit": "SOHO Consortium, LASCO, ESA, NASA",
  "explanation": "<b>  </b> \n<a href=\"http://www.nasa.gov/vision/universe/solarsystem/10.28Flare.html\">It</a> was one of the \n<a href=\"http://spaceweather.com/solarflares/topflares.html\">most powerful solar flares</a> in recorded history.  \n\nOccurring in 2003 and seen across the <a href=\"https://science.nasa.gov/ems/01_intro\">electromagnetic spectrum</a>, the \n<a href=\"https://solarsystem.nasa.gov/solar-system/sun/overview/\">Sun</a> \nbriefly became over 100 times brighter in \n<a href=\"https://science.nasa.gov/ems/11_xrays\">X-rays</a> \nthan normal. \n\nThe day after this \n<a href=\"https://www.nasa.gov/mission_pages/sunearth/news/X-class-flares.html\">tremendous X</a> 17 solar flare -- and subsequent \n<a href=\"https://helios.gsfc.nasa.gov/cme.html\">Coronal Mass Ejection</a> (CME) --  \n<a href=\"https://en.wikipedia.org/wiki/Solar_energetic_particles\">energetic particles</a> emitted from the explosions struck the Earth, \n<a href=\"ap031030.html\">creating</a> \n<a href=\"ap031104.html\">auroras</a> and affecting satellites.  \n\nThe spacecraft that took these frames -- \n<a href=\"https://www.nasa.gov/mission_pages/soho/index.html\">SOHO</a> -- was put in a <a href=\"https://upload.wikimedia.org/wikipedia/commons/thumb/b/bb/Baby_Turtle.jpg/1199px-Baby_Turtle.jpg\">turtle-like safe mode</a> to avoid further damage from this and \n<a href=\"https://www.nasa.gov/topics/solarsystem/features/halloween_storms.html\">subsequent solar particle storms</a>. \n\nThe \n<a href=\"https://sohowww.nascom.nasa.gov/hotshots/2003_10_28/\">featured time-lapse movie</a> condenses into 10 seconds \nevents that occurred over 4 hours.\n \nThe CME, visible around the central sun-shade, appears \nabout three-quarters of the way through the video, \nwhile frames toward the very end are progressively noisier as \n<a href=\"http://en.wikipedia.org/wiki/Proton\">protons</a> \nfrom the <a href=\"http://science.nasa.gov/ssl/pad/solar/cmes.htm\">explosions</a> strike SOHO's LASCO detector.  \n\nOne this day in 1859, the effects of an even more powerful solar storm caused telegraphs on Earth to spark in what is known as the \n<a href=\"https://en.wikipedia.org/wiki/Solar_storm_of_1859\">Carrington Event</a>.\n\nPowerful \n<a href=\"https://en.wikipedia.org/wiki/Halloween_solar_storms,_2003\">solar storms</a> such as these may create \n<a href=\"ap160830.html\">beautiful</a> \n<a href=\"ap970418.html\">aurora-filled skies</a>, \nbut they also pose a real danger as they can \n<a href=\"https://news.nationalgeographic.com/news/2011/03/110302-solar-flares-sun-storms-earth-danger-carrington-event-science/\">damage</a> \nsatellites and even power grids across the Earth.",
  "date": "2018-09-02",
  "service_version": "v1",
  "media_type": "video",
  "url": "https://www.youtube.com/embed/vzh7udgtDKA?rel=0"
}