{
  "title": "AE Aurigae and the Flaming Star Nebula",
  "explanation": "<b>  </b> \nWhy is AE Aurigae called the flaming star?\n\nFor one reason, the surrounding nebula\n<a href=\"ap031124.html\">IC 405</a> is named the\n<a href=\"http://www.daviddarling.info/encyclopedia/F/Flaming_Star_Nebula.html\">Flaming Star Nebula</a> because the region seems to harbor smoke, \neven though nothing is on fire, including interior star AE Aurigae.  \n\n<a href=\"http://en.wikipedia.org/wiki/Fire\">Fire</a>,\ntypically defined as the rapid molecular acquisition of\n<a href=\"http://periodic.lanl.gov/8.shtml\">oxygen</a>,\nhappens only when sufficient oxygen is present and is not important\nin such high-energy, low-oxygen environments.\n\nThe material that appears as\n<a href=\"http://www.youtube.com/watch?v=6UlsArvbTeo\">smoke</a> is mostly \n<a href=\"ap010113.html\">interstellar hydrogen</a>,\nbut does contain smoke-like dark filaments of carbon-rich\n<a href=\"http://en.wikipedia.org/wiki/Cosmic_dust\">dust grains</a>.\n\nThe bright star\n<a href=\"http://www.noao.edu/image_gallery/html/im0686.html\">AE Aurigae</a> is visible near the nebula center and is so \n<a href=\"http://www.webexhibits.org/causesofcolor/3.html\">hot</a> it is \n<a href=\"https://theconversation.com/is-red-warmer-than-blue-what-colours-can-tell-you-24614\">blue</a>, emitting light so energetic it knocks\n<a href=\"http://www.aip.org/history/electron/\">electrons</a> away\nfrom atoms in the surrounding gas.\n\nWhen an <a href=\"https://imagine.gsfc.nasa.gov/science/toolbox/atom.html\">atom</a> recaptures an electron, light is emitted creating the\nsurrounding <a href=\"emission_nebulae.html\">emission nebula</a>.\n\nThe \n<a href=\"http://adsabs.harvard.edu/abs/2004ApJ...616..257F\">Flaming\nStar nebula</a> lies about 1,500 \n<a href=\"http://chandra.harvard.edu/photo/cosmic_distance.html\">light\nyears</a> distant, spans about 5 light years, \nand is visible with a small telescope toward the\n<a href=\"http://www.astro.wisc.edu/~dolan/constellations/extra/\nconstellations.html\">constellation</a> of \n<a href=\"http://en.wikipedia.org/wiki/Auriga_(constellation)\">the\nCharioteer</a> (Auriga).",
  "date": "2018-02-25",
  "hdurl": "https://apod.nasa.gov/apod/image/1802/flamingstar_pugh_2666.jpg",
  "service_version": "v1",
  "copyright": "Martin Pugh",
  "media_type": "image",
  "url": "https://apod.nasa.gov/apod/image/1802/flamingstar_pugh_960.jpg"
}