{
  "title": "Human as Spaceship",
  "credit": "NASA, ESA, Hubble, and J. Maiz- Apellániz (IAA); Acknowledgement: D. De Martin; Human Image Copyright: Charis Tsevis; Composition: R. J. Nemiroff",
  "explanation": "<b>  </b> \nYou are a spaceship soaring through the universe.\n\nSo is your \n<a href=\"http://www.lifewithdogs.tv/wp-content/uploads/2015/11/11.10.15-head-tilt5.jpg\">dog</a>.\n\nWe all carry with us trillions of \n<a href=\"https://en.wikipedia.org/wiki/Microorganism\">microorganisms</a> as we go through life.\n\nThese multitudes of \n<a href=\"https://microbiologyonline.org/about-microbiology/introducing-microbes/bacteria\">bacteria</a>, \n<a href=\"https://microbiologyonline.org/about-microbiology/introducing-microbes/fungi\">fungi</a>, and \n<a href=\"https://microbiologyonline.org/about-microbiology/introducing-microbes/archaea\">archaea</a> have different \n<a href=\"ap120821.html\">DNA</a> than you.\n\nCollectively called your microbiome, your \n<a href=\"http://www.nasa.gov/exploration/humanresearch/Microbial-Creatures-in-Space.html\">shipmates</a> outnumber your own cells.\n\nYour crew members form \n<a href=\"http://www.nature.com/subjects/communities\">communities</a>, \nhelp \n<a href=\"http://www.typesofbacteria.co.uk/friendly-bacteria-digestive-system.html\">digest food</a>, engage in \n<a href=\"http://science.sciencemag.org/content/336/6086/1246\">battles</a> \nagainst intruders, and sometimes commute on a \n<a href=\"http://blogs.scientificamerican.com/lab-rat/how-bacteria-sneak-into-your-blood-through-your-mouth/\">liquid superhighway</a> from one end of \n<a href=\"http://www.npr.org/sections/health-shots/2012/06/13/154913334/finally-a-map-of-all-the-microbes-on-your-body\">your body</a> to the other. \n\nMuch of what your \n<a href=\"https://www.youtube.com/watch?v=5DTrENdWvvM\">microbiome</a> does, however, \n<a href=\"https://www.youtube.com/watch?v=i-icXZ2tMRM\">remains unknown</a>.\n\nYou are the \n<a href=\"http://www.universetoday.com/wp-content/uploads/2013/05/tribbles.jpg\">captain</a>, but being nice to \n<a href=\"http://learn.genetics.utah.edu/content/microbiome/changing/\">your crew</a> \nmay allow you to explore more of your \n<a href=\"ap100713.html\">local cosmos</a>.",
  "date": "2019-08-18",
  "hdurl": "https://apod.nasa.gov/apod/image/1908/HumanSpaceship2_TsevisHubbleRJN_2000.jpg",
  "service_version": "v1",
  "copyright": "Charis Tsevis; Composition: R. J. Nemiroff",
  "media_type": "image",
  "url": "https://apod.nasa.gov/apod/image/1908/HumanSpaceship2_TsevisHubbleRJN_960.jpg"
}