{
  "title": "M87's Central Black Hole in Polarized Light",
  "credit": "Event Horizon Telescope Collaboration; Text: Jayanne English (U. Manitoba)",
  "explanation": "<b>  </b> \nTo play on \n<a href=\"https://youtu.be/v0CG5TM0oa4\">Carl Sagan</a>’s \n<a href=\"https://www.sciencemag.org/news/2010/02/making-apple-pie-and-creation-universe\">famous words</a> \n\"If you wish to make black hole jets, you must first create magnetic fields.\"\n\nThe <a href=\"https://eventhorizontelescope.org/blog/astronomers-image-magnetic-fields-edge-m87s-black-hole\">featured image</a> represents the \n<a href=\"https://insidetheperimeter.ca/opening-up-closure-traces/\">detected</a> intrinsic spin direction \n(<a href=\"https://www.rfvenue.com/blog/2014/12/15/wave-polarization-explained\">polarization</a>) of \n<a href=\"https://science.nasa.gov/ems/05_radiowaves\">radio waves</a>. \n\nThe <a href=\"https://ixpe.msfc.nasa.gov/creation.html\">polarizationi</a> is produced by the powerful \n<a href=\"https://youtu.be/8llkHQtaOlg\">magnetic field</a> \nsurrounding the supermassive black hole at the center of \n<a href=\"ap040616.html\">elliptical galaxy</a> \n<a href=\"https://en.wikipedia.org/wiki/Messier_87\">M87</a>.\n\nThe radio waves were detected by the \n<a href=\"https://eventhorizontelescope.org/about\">Event Horizon Telescope</a> (EHT), \nwhich combines data from radio telescopes <a href=\"https://en.wikipedia.org/wiki/Event_Horizon_Telescope#/media/File:The_Event_Horizon_Telescope_and_Global_mm-VLBI_Array_on_the_Earth.jpg\">distributed worldwide</a>. \n\nThe \n<a href=\"https://iopscience.iop.org/article/10.3847/2041-8213/abe71d\">polarization structure</a>, mapped using computer generated \n<a href=\"http://www.zhanpingliu.org/research/flowvis/LIC/LIC.htm\">flow lines</a>, \nis overlaid on \n<a href=\"https://eventhorizontelescope.org/press-release-april-10-2019-astronomers-capture-first-image-black-hole\">EHT’s famous black hole image</a>, first published in 2019.\n\nThe full 3-D magnetic field is \n<a href=\"https://barkpost.com/wp-content/uploads/2014/06/toiletpaperdog.jpg\">complex</a>. \n\nPreliminary \n<a href=\"https://iopscience.iop.org/article/10.3847/2041-8213/abe4de\">analyses indicate</a> that parts of the field circle around the \nblack hole along with the \n<a href=\"ap200825.html\">accreting matter</a>, as expected. \n\nHowever, \n<a href=\"https://aasnova.org/2021/03/24/event-horizon-telescope-traces-magnetic-fields-around-a-black-hole/\">another component</a> seemingly veers vertically away from the black hole. \n\nThis component could \n<a href=\"https://youtu.be/8w1BHjOv7VM\">explain how</a> \nmatter resists falling in and is instead launched into \n<a href=\"https://hubblesite.org/contents/media/images/2000/20/968-Image.html\">M87’s jet</a>.",
  "date": "2021-03-31",
  "hdurl": "https://apod.nasa.gov/apod/image/2103/M87bhPolarized_Eht_3414.jpg",
  "service_version": "v1",
  "media_type": "image",
  "url": "https://apod.nasa.gov/apod/image/2103/M87bhPolarized_Eht_960.jpg"
}